.DS_Store
automatatron/__init__.py
automatatron/engine.py
automatatron/version.py
automatatron-1.1.0.dist-info/DESCRIPTION.rst
automatatron-1.1.0.dist-info/METADATA
automatatron-1.1.0.dist-info/metadata.json
automatatron-1.1.0.dist-info/RECORD
automatatron-1.1.0.dist-info/top_level.txt
automatatron-1.1.0.dist-info/WHEEL
