Metadata-Version: 2.0
Name: automatatron
Version: 1.1.0
Summary: Python Cellular Automata Engine
Home-page: http://github.com/rhyolight/automatatron
Author: Matthew Taylor
Author-email: matt@numenta.org
License: MIT
Keywords: cellular automata
Platform: UNKNOWN
Classifier: Development Status :: 5 - Production/Stable
Classifier: Environment :: Console
Classifier: Intended Audience :: Developers
Classifier: License :: OSI Approved :: MIT License
Classifier: Natural Language :: English
Classifier: Operating System :: OS Independent
Classifier: Programming Language :: Python
Requires-Dist: nose
Requires-Dist: coverage
